llama_index/storage/chat_store/sqlite/__init__.py
llama_index/storage/chat_store/sqlite/base.py
llama_index_storage_chat_store_sqlite-0.2.1.dist-info/METADATA
llama_index_storage_chat_store_sqlite-0.2.1.dist-info/WHEEL
llama_index_storage_chat_store_sqlite-0.2.1.dist-info/licenses/LICENSE
llama_index_storage_chat_store_sqlite-0.2.1.dist-info/RECORD
