Metadata-Version: 2.4
Name: llama-index-storage-chat-store-sqlite
Version: 0.2.1
Summary: llama-index storage-chat-store sqlite integration
Author-email: Your Name <you@example.com>
License-Expression: MIT
License-File: LICENSE
Requires-Python: <4.0,>=3.9
Requires-Dist: aiosqlite<0.22,>=0.21.0
Requires-Dist: llama-index-core<0.15,>=0.13.0
